maquinitas/__init__.py
maquinitas-0.0.1.dist-info/LICENSE
maquinitas-0.0.1.dist-info/METADATA
maquinitas-0.0.1.dist-info/WHEEL
maquinitas-0.0.1.dist-info/top_level.txt
maquinitas-0.0.1.dist-info/RECORD
