Metadata-Version: 2.1
Name: maquinitas
Version: 0.0.1
Summary: Control of MIDI hardware devices
Home-page: https://github.com/maquinitas/maquinitas-foxdot
Author: Aarón Montoya-Moraga
Author-email: montoyamoraga@gmail.com.com
License: UNKNOWN
Platform: UNKNOWN
Classifier: Programming Language :: Python :: 3
Classifier: License :: OSI Approved :: MIT License
Classifier: Operating System :: OS Independent
